<?xml version="1.0" encoding="UTF-8"?>

<mule xmlns:ee="http://www.mulesoft.org/schema/mule/ee/core" xmlns="http://www.mulesoft.org/schema/mule/core"
	xmlns:doc="http://www.mulesoft.org/schema/mule/documentation"
	xmlns:xsi="http://www.w3.org/2001/XMLSchema-instance" xsi:schemaLocation="http://www.mulesoft.org/schema/mule/core http://www.mulesoft.org/schema/mule/core/current/mule.xsd
http://www.mulesoft.org/schema/mule/ee/core http://www.mulesoft.org/schema/mule/ee/core/current/mule-ee.xsd">
	<sub-flow name="common-initialize-variableSub_Flow" doc:id="2ebd7865-135d-4093-af3f-572a25bbd9e6" >
		<ee:transform doc:name="Transform Message" doc:id="36b376ca-8ad2-4bed-b0f0-b4a1b321d8fb" >
			<ee:message >
			</ee:message>
			<ee:variables >
				<ee:set-variable variableName="requesttime" ><![CDATA[now()]]></ee:set-variable>
				<ee:set-variable variableName="requestqueryParam" ><![CDATA[attributes.queryParams]]></ee:set-variable>
				<ee:set-variable variableName="requesturiParam" ><![CDATA[attributes.uriParams]]></ee:set-variable>
				<ee:set-variable variableName="requestHeader" ><![CDATA[attributes.headers

]]></ee:set-variable>
				<ee:set-variable variableName="requestPayload" ><![CDATA[%dw 2.0
output application/json
---
payload
]]></ee:set-variable>
			</ee:variables>
		</ee:transform>
	</sub-flow>
</mule>
